[{"Usage_ID":"00","Usage_Name":"Reserved","Usage_Types":"Undefined"},{"Usage_ID":"01","Usage_Name":"Consumer Control","Usage_Types":"CA"},{"Usage_ID":"02","Usage_Name":"Numeric Key Pad","Usage_Types":"NAry"},{"Usage_ID":"03","Usage_Name":"Programmable Buttons","Usage_Types":"NAry"},{"Usage_ID":"04","Usage_Name":"Microphone","Usage_Types":"CA"},{"Usage_ID":"05","Usage_Name":"Headphone","Usage_Types":"CA"},{"Usage_ID":"06","Usage_Name":"Graphic Equalizer","Usage_Types":"CA"},{"Usage_ID":"07-1F","Usage_Name":"Reserved","Usage_Types":"Undefined"},{"Usage_ID":"20","Usage_Name":"+10","Usage_Types":"OSC"},{"Usage_ID":"21","Usage_Name":"+100","Usage_Types":"OSC"},{"Usage_ID":"22","Usage_Name":"AM/PM","Usage_Types":"OSC"},{"Usage_ID":"23-2F","Usage_Name":"Reserved","Usage_Types":"Undefined"},{"Usage_ID":"30","Usage_Name":"Power","Usage_Types":"OOC"},{"Usage_ID":"31","Usage_Name":"Reset","Usage_Types":"OSC"},{"Usage_ID":"32","Usage_Name":"Sleep","Usage_Types":"OSC"},{"Usage_ID":"33","Usage_Name":"Sleep After","Usage_Types":"OSC"},{"Usage_ID":"34","Usage_Name":"Sleep Mode","Usage_Types":"RTC"},{"Usage_ID":"35","Usage_Name":"Illumination","Usage_Types":"OOC"},{"Usage_ID":"36","Usage_Name":"Function Buttons","Usage_Types":"NAry"},{"Usage_ID":"37-3F","Usage_Name":"Reserved","Usage_Types":"Undefined"},{"Usage_ID":"40","Usage_Name":"Menu","Usage_Types":"OOC"},{"Usage_ID":"41","Usage_Name":"Menu Pick","Usage_Types":"OSC"},{"Usage_ID":"42","Usage_Name":"Menu Up","Usage_Types":"OSC"},{"Usage_ID":"43","Usage_Name":"Menu Down","Usage_Types":"OSC"},{"Usage_ID":"44","Usage_Name":"Menu Left","Usage_Types":"OSC"},{"Usage_ID":"45","Usage_Name":"Menu Right","Usage_Types":"OSC"},{"Usage_ID":"46","Usage_Name":"Menu Escape","Usage_Types":"OSC"},{"Usage_ID":"47","Usage_Name":"Menu Value Increase","Usage_Types":"OSC"},{"Usage_ID":"48","Usage_Name":"Menu Value Decrease","Usage_Types":"OSC"},{"Usage_ID":"49-5F","Usage_Name":"Reserved","Usage_Types":"Undefined"},{"Usage_ID":"60","Usage_Name":"Data On Screen","Usage_Types":"OOC"},{"Usage_ID":"61","Usage_Name":"Closed Caption","Usage_Types":"OOC"},{"Usage_ID":"62","Usage_Name":"Closed Caption Select","Usage_Types":"Sel"},{"Usage_ID":"63","Usage_Name":"VCR/TV","Usage_Types":"OOC"},{"Usage_ID":"64","Usage_Name":"Broadcast Mode","Usage_Types":"OSC"},{"Usage_ID":"65","Usage_Name":"Snapshot","Usage_Types":"OSC"},{"Usage_ID":"66","Usage_Name":"Still","Usage_Types":"OSC"},{"Usage_ID":"67","Usage_Name":"Picture-in-Picture Toggle","Usage_Types":"OSC"},{"Usage_ID":"68","Usage_Name":"Picture-in-Picture Swap","Usage_Types":"OSC"},{"Usage_ID":"69","Usage_Name":"Red Menu Button","Usage_Types":"MC"},{"Usage_ID":"6A","Usage_Name":"Green Menu Button","Usage_Types":"MC"},{"Usage_ID":"6B","Usage_Name":"Blue Menu Button","Usage_Types":"MC"},{"Usage_ID":"6C","Usage_Name":"Yellow Menu Button","Usage_Types":"MC"},{"Usage_ID":"6D","Usage_Name":"Aspect","Usage_Types":"OSC"},{"Usage_ID":"6E","Usage_Name":"3D Mode Select","Usage_Types":"Sel"},{"Usage_ID":"6F","Usage_Name":"Display Brightness Increment","Usage_Types":"RTC"},{"Usage_ID":"70","Usage_Name":"Display Brightness Decrement","Usage_Types":"RTC"},{"Usage_ID":"71","Usage_Name":"Display Brightness","Usage_Types":"LC"},{"Usage_ID":"72","Usage_Name":"Display Backlight Toggle","Usage_Types":"OOC"},{"Usage_ID":"73","Usage_Name":"Display Set Brightness to Minimum","Usage_Types":"OSC"},{"Usage_ID":"74","Usage_Name":"Display Set Brightness to Maximum","Usage_Types":"OSC"},{"Usage_ID":"75","Usage_Name":"Display Set Auto Brightness","Usage_Types":"OOC"},{"Usage_ID":"76","Usage_Name":"Camera Access Enabled","Usage_Types":"OOC"},{"Usage_ID":"77","Usage_Name":"Camera Access Disabled","Usage_Types":"OOC"},{"Usage_ID":"78","Usage_Name":"Camera Access Toggle","Usage_Types":"OOC"},{"Usage_ID":"79","Usage_Name":"Keyboard Brightness Increment","Usage_Types":"OSC"},{"Usage_ID":"7A","Usage_Name":"Keyboard Brightness Decrement","Usage_Types":"OSC"},{"Usage_ID":"7B","Usage_Name":"Keyboard Backlight Set Level","Usage_Types":"LC"},{"Usage_ID":"7C","Usage_Name":"Keyboard Backlight OOC","Usage_Types":"OOC"},{"Usage_ID":"7D","Usage_Name":"Keyboard Backlight Set Minimum","Usage_Types":"OSC"},{"Usage_ID":"7E","Usage_Name":"Keyboard Backlight Set Maximum","Usage_Types":"OSC"},{"Usage_ID":"7F","Usage_Name":"Keyboard Backlight Auto","Usage_Types":"OOC"},{"Usage_ID":"80","Usage_Name":"Selection","Usage_Types":"Sel"},{"Usage_ID":"81","Usage_Name":"Assign Selection","Usage_Types":"Sel"},{"Usage_ID":"82","Usage_Name":"Mode Step","Usage_Types":"OSC"},{"Usage_ID":"83","Usage_Name":"Recall Last","Usage_Types":"OSC"},{"Usage_ID":"84","Usage_Name":"Enter Channel","Usage_Types":"OSC"},{"Usage_ID":"85","Usage_Name":"Order Movie","Usage_Types":"OSC"},{"Usage_ID":"86","Usage_Name":"Channel","Usage_Types":"LC"},{"Usage_ID":"87","Usage_Name":"Media Selection","Usage_Types":"Sel"},{"Usage_ID":"88","Usage_Name":"Media Select Computer","Usage_Types":"Sel"},{"Usage_ID":"89","Usage_Name":"Media Select TV","Usage_Types":"Sel"},{"Usage_ID":"8A","Usage_Name":"Media Select WWW","Usage_Types":"Sel"},{"Usage_ID":"8B","Usage_Name":"Media Select DVD","Usage_Types":"Sel"},{"Usage_ID":"8C","Usage_Name":"Media Select Telephone","Usage_Types":"Sel"},{"Usage_ID":"8D","Usage_Name":"Media Select Program Guide","Usage_Types":"Sel"},{"Usage_ID":"8E","Usage_Name":"Media Select Video Phone","Usage_Types":"Sel"},{"Usage_ID":"8F","Usage_Name":"Media Select Games","Usage_Types":"Sel"},{"Usage_ID":"90","Usage_Name":"Media Select Messages","Usage_Types":"Sel"},{"Usage_ID":"91","Usage_Name":"Media Select CD","Usage_Types":"Sel"},{"Usage_ID":"92","Usage_Name":"Media Select VCR","Usage_Types":"Sel"},{"Usage_ID":"93","Usage_Name":"Media Select Tuner","Usage_Types":"Sel"},{"Usage_ID":"94","Usage_Name":"Quit","Usage_Types":"OSC"},{"Usage_ID":"95","Usage_Name":"Help","Usage_Types":"OOC"},{"Usage_ID":"96","Usage_Name":"Media Select Tape","Usage_Types":"Sel"},{"Usage_ID":"97","Usage_Name":"Media Select Cable","Usage_Types":"Sel"},{"Usage_ID":"98","Usage_Name":"Media Select Satellite","Usage_Types":"Sel"},{"Usage_ID":"99","Usage_Name":"Media Select Security","Usage_Types":"Sel"},{"Usage_ID":"9A","Usage_Name":"Media Select Home","Usage_Types":"Sel"},{"Usage_ID":"9B","Usage_Name":"Media Select Call","Usage_Types":"Sel"},{"Usage_ID":"9C","Usage_Name":"Channel Increment","Usage_Types":"OSC"},{"Usage_ID":"9D","Usage_Name":"Channel Decrement","Usage_Types":"OSC"},{"Usage_ID":"9E","Usage_Name":"Media Select SAP","Usage_Types":"Sel"},{"Usage_ID":"9F-9F","Usage_Name":"Reserved","Usage_Types":"Undefined"},{"Usage_ID":"A0","Usage_Name":"VCR Plus","Usage_Types":"OSC"},{"Usage_ID":"A1","Usage_Name":"Once","Usage_Types":"OSC"},{"Usage_ID":"A2","Usage_Name":"Daily","Usage_Types":"OSC"},{"Usage_ID":"A3","Usage_Name":"Weekly","Usage_Types":"OSC"},{"Usage_ID":"A4","Usage_Name":"Monthly","Usage_Types":"OSC"},{"Usage_ID":"A5-AF","Usage_Name":"Reserved","Usage_Types":"Undefined"},{"Usage_ID":"B0","Usage_Name":"Play","Usage_Types":"OOC"},{"Usage_ID":"B1","Usage_Name":"Pause","Usage_Types":"OOC"},{"Usage_ID":"B2","Usage_Name":"Record","Usage_Types":"OOC"},{"Usage_ID":"B3","Usage_Name":"Fast Forward","Usage_Types":"OOC"},{"Usage_ID":"B4","Usage_Name":"Rewind","Usage_Types":"OOC"},{"Usage_ID":"B5","Usage_Name":"Scan Next Track","Usage_Types":"OSC"},{"Usage_ID":"B6","Usage_Name":"Scan Previous Track","Usage_Types":"OSC"},{"Usage_ID":"B7","Usage_Name":"Stop","Usage_Types":"OSC"},{"Usage_ID":"B8","Usage_Name":"Eject","Usage_Types":"OSC"},{"Usage_ID":"B9","Usage_Name":"Random Play","Usage_Types":"OOC"},{"Usage_ID":"BA","Usage_Name":"Select Disc","Usage_Types":"Sel"},{"Usage_ID":"BB","Usage_Name":"Enter Disc","Usage_Types":"MC"},{"Usage_ID":"BC","Usage_Name":"Repeat","Usage_Types":"OSC"},{"Usage_ID":"BD","Usage_Name":"Tracking","Usage_Types":"LC"},{"Usage_ID":"BE","Usage_Name":"Track Normal","Usage_Types":"OSC"},{"Usage_ID":"BF","Usage_Name":"Slow Tracking","Usage_Types":"LC"},{"Usage_ID":"C0","Usage_Name":"Frame Forward","Usage_Types":"RTC"},{"Usage_ID":"C1","Usage_Name":"Frame Back","Usage_Types":"RTC"},{"Usage_ID":"C2","Usage_Name":"Mark","Usage_Types":"OSC"},{"Usage_ID":"C3","Usage_Name":"Clear Mark","Usage_Types":"OSC"},{"Usage_ID":"C4","Usage_Name":"Repeat From Mark","Usage_Types":"OOC"},{"Usage_ID":"C5","Usage_Name":"Return To Mark","Usage_Types":"OSC"},{"Usage_ID":"C6","Usage_Name":"Search Mark Forward","Usage_Types":"OSC"},{"Usage_ID":"C7","Usage_Name":"Search Mark Backwards","Usage_Types":"OSC"},{"Usage_ID":"C8","Usage_Name":"Counter Reset","Usage_Types":"OSC"},{"Usage_ID":"C9","Usage_Name":"Show Counter","Usage_Types":"OSC"},{"Usage_ID":"CA","Usage_Name":"Tracking Increment","Usage_Types":"CA"},{"Usage_ID":"CB","Usage_Name":"Tracking Decrement","Usage_Types":"RTC"},{"Usage_ID":"CC","Usage_Name":"Stop/Eject","Usage_Types":"OSC"},{"Usage_ID":"CD","Usage_Name":"Play/Pause","Usage_Types":"OSC"},{"Usage_ID":"CE","Usage_Name":"Play/Skip","Usage_Types":"OSC"},{"Usage_ID":"CF","Usage_Name":"Voice Command","Usage_Types":"OSC"},{"Usage_ID":"D0","Usage_Name":"Invoke Capture Interface","Usage_Types":"Sel"},{"Usage_ID":"D1","Usage_Name":"Start or Stop Game Recording","Usage_Types":"Sel"},{"Usage_ID":"D2","Usage_Name":"Historical Game Capture","Usage_Types":"Sel"},{"Usage_ID":"D3","Usage_Name":"Capture Game Screenshot","Usage_Types":"Sel"},{"Usage_ID":"D4","Usage_Name":"Show or Hide Recording Indicator","Usage_Types":"Sel"},{"Usage_ID":"D5","Usage_Name":"Start or Stop Microphone Capture","Usage_Types":"Sel"},{"Usage_ID":"D6","Usage_Name":"Start or Stop Camera Capture","Usage_Types":"Sel"},{"Usage_ID":"D7","Usage_Name":"Start or Stop Game Broadcast","Usage_Types":"Sel"},{"Usage_ID":"D8","Usage_Name":"Start or Stop Voice Dictation Session","Usage_Types":"OOC"},{"Usage_ID":"D9","Usage_Name":"Invoke/Dismiss Emoji Picker","Usage_Types":"OOC"},{"Usage_ID":"DA-DF","Usage_Name":"Reserved","Usage_Types":"DF"},{"Usage_ID":"E0","Usage_Name":"Volume","Usage_Types":"LC"},{"Usage_ID":"E1","Usage_Name":"Balance","Usage_Types":"LC"},{"Usage_ID":"E2","Usage_Name":"Mute","Usage_Types":"OOC"},{"Usage_ID":"E3","Usage_Name":"Bass","Usage_Types":"LC"},{"Usage_ID":"E4","Usage_Name":"Treble","Usage_Types":"LC"},{"Usage_ID":"E5","Usage_Name":"Bass Boost","Usage_Types":"OOC"},{"Usage_ID":"E6","Usage_Name":"Surround Mode","Usage_Types":"OSC"},{"Usage_ID":"E7","Usage_Name":"Loudness","Usage_Types":"OOC"},{"Usage_ID":"E8","Usage_Name":"MPX","Usage_Types":"OOC"},{"Usage_ID":"E9","Usage_Name":"Volume Increment","Usage_Types":"RTC"},{"Usage_ID":"EA","Usage_Name":"Volume Decrement","Usage_Types":"RTC"},{"Usage_ID":"EB-EF","Usage_Name":"Reserved","Usage_Types":"Undefined"},{"Usage_ID":"F0","Usage_Name":"Speed Select","Usage_Types":"Sel"},{"Usage_ID":"F1","Usage_Name":"Playback Speed","Usage_Types":"NAry"},{"Usage_ID":"F2","Usage_Name":"Standard Play","Usage_Types":"Sel"},{"Usage_ID":"F3","Usage_Name":"Long Play","Usage_Types":"Sel"},{"Usage_ID":"F4","Usage_Name":"Extended Play","Usage_Types":"Sel"},{"Usage_ID":"F5","Usage_Name":"Slow","Usage_Types":"OSC"},{"Usage_ID":"F6-FF","Usage_Name":"Reserved","Usage_Types":"Undefined"},{"Usage_ID":"100","Usage_Name":"Fan Enable","Usage_Types":"OOC"},{"Usage_ID":"101","Usage_Name":"Fan Speed","Usage_Types":"LC"},{"Usage_ID":"102","Usage_Name":"Light Enable","Usage_Types":"OOC"},{"Usage_ID":"103","Usage_Name":"Light Illumination Level","Usage_Types":"LC"},{"Usage_ID":"104","Usage_Name":"Climate Control Enable","Usage_Types":"OOC"},{"Usage_ID":"105","Usage_Name":"Room Temperature","Usage_Types":"LC"},{"Usage_ID":"106","Usage_Name":"Security Enable","Usage_Types":"OOC"},{"Usage_ID":"107","Usage_Name":"Fire Alarm","Usage_Types":"OSC"},{"Usage_ID":"108","Usage_Name":"Police Alarm","Usage_Types":"OSC"},{"Usage_ID":"109","Usage_Name":"Proximity","Usage_Types":"LC"},{"Usage_ID":"10A","Usage_Name":"Motion","Usage_Types":"OSC"},{"Usage_ID":"10B","Usage_Name":"Duress Alarm","Usage_Types":"OSC"},{"Usage_ID":"10C","Usage_Name":"Holdup Alarm","Usage_Types":"OSC"},{"Usage_ID":"10D","Usage_Name":"Medical Alarm","Usage_Types":"OSC"},{"Usage_ID":"10E-14F","Usage_Name":"Reserved","Usage_Types":"Undefined"},{"Usage_ID":"150","Usage_Name":"Balance Right","Usage_Types":"RTC"},{"Usage_ID":"151","Usage_Name":"Balance Left","Usage_Types":"RTC"},{"Usage_ID":"152","Usage_Name":"Bass Increment","Usage_Types":"RTC"},{"Usage_ID":"153","Usage_Name":"Bass Decrement","Usage_Types":"RTC"},{"Usage_ID":"154","Usage_Name":"Treble Increment","Usage_Types":"RTC"},{"Usage_ID":"155","Usage_Name":"Treble Decrement","Usage_Types":"RTC"},{"Usage_ID":"156-15F","Usage_Name":"Reserved","Usage_Types":"Undefined"},{"Usage_ID":"160","Usage_Name":"Speaker System","Usage_Types":"CL"},{"Usage_ID":"161","Usage_Name":"Channel Left","Usage_Types":"CL"},{"Usage_ID":"162","Usage_Name":"Channel Right","Usage_Types":"CL"},{"Usage_ID":"163","Usage_Name":"Channel Center","Usage_Types":"CL"},{"Usage_ID":"164","Usage_Name":"Channel Front","Usage_Types":"CL"},{"Usage_ID":"165","Usage_Name":"Channel Center Front","Usage_Types":"CL"},{"Usage_ID":"166","Usage_Name":"Channel Side","Usage_Types":"CL"},{"Usage_ID":"167","Usage_Name":"Channel Surround","Usage_Types":"CL"},{"Usage_ID":"168","Usage_Name":"Channel Low Frequency Enhancement","Usage_Types":"CL"},{"Usage_ID":"169","Usage_Name":"Channel Top","Usage_Types":"CL"},{"Usage_ID":"16A","Usage_Name":"Channel Unknown","Usage_Types":"CL"},{"Usage_ID":"16B-16F","Usage_Name":"Reserved","Usage_Types":"Undefined"},{"Usage_ID":"170","Usage_Name":"Sub-channel","Usage_Types":"LC"},{"Usage_ID":"171","Usage_Name":"Sub-channel Increment","Usage_Types":"OSC"},{"Usage_ID":"172","Usage_Name":"Sub-channel Decrement","Usage_Types":"OSC"},{"Usage_ID":"173","Usage_Name":"Alternate Audio Increment","Usage_Types":"OSC"},{"Usage_ID":"174","Usage_Name":"Alternate Audio Decrement","Usage_Types":"OSC"},{"Usage_ID":"175-17F","Usage_Name":"Reserved","Usage_Types":"Undefined"},{"Usage_ID":"180","Usage_Name":"Application Launch Buttons","Usage_Types":"NAry"},{"Usage_ID":"181","Usage_Name":"AL Launch Button Configuration Tool","Usage_Types":"Sel"},{"Usage_ID":"182","Usage_Name":"AL Programmable Button Configuration","Usage_Types":"Sel"},{"Usage_ID":"183","Usage_Name":"AL Consumer Control Configuration","Usage_Types":"Sel"},{"Usage_ID":"184","Usage_Name":"AL Word Processor","Usage_Types":"Sel"},{"Usage_ID":"185","Usage_Name":"AL Text Editor","Usage_Types":"Sel"},{"Usage_ID":"186","Usage_Name":"AL Spreadsheet","Usage_Types":"Sel"},{"Usage_ID":"187","Usage_Name":"AL Graphics Editor","Usage_Types":"Sel"},{"Usage_ID":"188","Usage_Name":"AL Presentation App","Usage_Types":"Sel"},{"Usage_ID":"189","Usage_Name":"AL Database App","Usage_Types":"Sel"},{"Usage_ID":"18A","Usage_Name":"AL Email Reader","Usage_Types":"Sel"},{"Usage_ID":"18B","Usage_Name":"AL Newsreader","Usage_Types":"Sel"},{"Usage_ID":"18C","Usage_Name":"AL Voicemail","Usage_Types":"Sel"},{"Usage_ID":"18D","Usage_Name":"AL Contacts/Address Book","Usage_Types":"Sel"},{"Usage_ID":"18E","Usage_Name":"AL Calendar/Schedule","Usage_Types":"Sel"},{"Usage_ID":"18F","Usage_Name":"AL Task/Project Manager","Usage_Types":"Sel"},{"Usage_ID":"190","Usage_Name":"AL Log/Journal/Timecard","Usage_Types":"Sel"},{"Usage_ID":"191","Usage_Name":"AL Checkbook/Finance","Usage_Types":"Sel"},{"Usage_ID":"192","Usage_Name":"AL Calculator","Usage_Types":"Sel"},{"Usage_ID":"193","Usage_Name":"AL A/V Capture/Playback","Usage_Types":"Sel"},{"Usage_ID":"194","Usage_Name":"AL Local Machine Browser","Usage_Types":"Sel"},{"Usage_ID":"195","Usage_Name":"AL LAN/WAN Browser","Usage_Types":"Sel"},{"Usage_ID":"196","Usage_Name":"AL Internet Browser","Usage_Types":"Sel"},{"Usage_ID":"197","Usage_Name":"AL Remote Networking/ISP Connect","Usage_Types":"Sel"},{"Usage_ID":"198","Usage_Name":"AL Network Conference","Usage_Types":"Sel"},{"Usage_ID":"199","Usage_Name":"AL Network Chat","Usage_Types":"Sel"},{"Usage_ID":"19A","Usage_Name":"AL Telephony/Dialer","Usage_Types":"Sel"},{"Usage_ID":"19B","Usage_Name":"AL Logon","Usage_Types":"Sel"},{"Usage_ID":"19C","Usage_Name":"AL Logoff","Usage_Types":"Sel"},{"Usage_ID":"19D","Usage_Name":"AL Logon/Logoff","Usage_Types":"Sel"},{"Usage_ID":"19E","Usage_Name":"AL Terminal Lock/Screensaver","Usage_Types":"Sel"},{"Usage_ID":"19F","Usage_Name":"AL Control Panel","Usage_Types":"Sel"},{"Usage_ID":"1A0","Usage_Name":"AL Command Line Processor/Run","Usage_Types":"Sel"},{"Usage_ID":"1A1","Usage_Name":"AL Process/Task Manager","Usage_Types":"Sel"},{"Usage_ID":"1A2","Usage_Name":"AL Select Task/Application","Usage_Types":"Sel"},{"Usage_ID":"1A3","Usage_Name":"AL Next Task/Application","Usage_Types":"Sel"},{"Usage_ID":"1A4","Usage_Name":"AL Previous Task/Application","Usage_Types":"Sel"},{"Usage_ID":"1A5","Usage_Name":"AL Preemptive Halt Task/Application","Usage_Types":"Sel"},{"Usage_ID":"1A6","Usage_Name":"AL Integrated Help Center","Usage_Types":"Sel"},{"Usage_ID":"1A7","Usage_Name":"AL Documents","Usage_Types":"Sel"},{"Usage_ID":"1A8","Usage_Name":"AL Thesaurus","Usage_Types":"Sel"},{"Usage_ID":"1A9","Usage_Name":"AL Dictionary","Usage_Types":"Sel"},{"Usage_ID":"1AA","Usage_Name":"AL Desktop","Usage_Types":"Sel"},{"Usage_ID":"1AB","Usage_Name":"AL Spell Check","Usage_Types":"Sel"},{"Usage_ID":"1AC","Usage_Name":"AL Grammar Check","Usage_Types":"Sel"},{"Usage_ID":"1AD","Usage_Name":"AL Wireless Status","Usage_Types":"Sel"},{"Usage_ID":"1AE","Usage_Name":"AL Keyboard Layout","Usage_Types":"Sel"},{"Usage_ID":"1AF","Usage_Name":"AL Virus Protection","Usage_Types":"Sel"},{"Usage_ID":"1B0","Usage_Name":"AL Encryption","Usage_Types":"Sel"},{"Usage_ID":"1B1","Usage_Name":"AL Screen Saver","Usage_Types":"Sel"},{"Usage_ID":"1B2","Usage_Name":"AL Alarms","Usage_Types":"Sel"},{"Usage_ID":"1B3","Usage_Name":"AL Clock","Usage_Types":"Sel"},{"Usage_ID":"1B4","Usage_Name":"AL File Browser","Usage_Types":"Sel"},{"Usage_ID":"1B5","Usage_Name":"AL Power Status","Usage_Types":"Sel"},{"Usage_ID":"1B6","Usage_Name":"AL Image Browser","Usage_Types":"Sel"},{"Usage_ID":"1B7","Usage_Name":"AL Audio Browser","Usage_Types":"Sel"},{"Usage_ID":"1B8","Usage_Name":"AL Movie Browser","Usage_Types":"Sel"},{"Usage_ID":"1B9","Usage_Name":"AL Digital Rights Manager","Usage_Types":"Sel"},{"Usage_ID":"1BA","Usage_Name":"AL Digital Wallet","Usage_Types":"Sel"},{"Usage_ID":"1BB-1BB","Usage_Name":"Reserved","Usage_Types":"Undefined"},{"Usage_ID":"1BC","Usage_Name":"AL Instant Messaging","Usage_Types":"Sel"},{"Usage_ID":"1BD","Usage_Name":"AL OEM Features/ Tips/Tutorial Browser","Usage_Types":"Sel"},{"Usage_ID":"1BE","Usage_Name":"AL OEM Help","Usage_Types":"Sel"},{"Usage_ID":"1BF","Usage_Name":"AL Online Community","Usage_Types":"Sel"},{"Usage_ID":"1C0","Usage_Name":"AL Entertainment Content Browser","Usage_Types":"Sel"},{"Usage_ID":"1C1","Usage_Name":"AL Online Shopping Browser","Usage_Types":"Sel"},{"Usage_ID":"1C2","Usage_Name":"AL SmartCard Information/Help","Usage_Types":"Sel"},{"Usage_ID":"1C3","Usage_Name":"AL Market Monitor/Finance Browser","Usage_Types":"Sel"},{"Usage_ID":"1C4","Usage_Name":"AL Customized Corporate News Browser","Usage_Types":"Sel"},{"Usage_ID":"1C5","Usage_Name":"AL Online Activity Browser","Usage_Types":"Sel"},{"Usage_ID":"1C6","Usage_Name":"AL Research/Search Browser","Usage_Types":"Sel"},{"Usage_ID":"1C7","Usage_Name":"AL Audio Player","Usage_Types":"Sel"},{"Usage_ID":"1C8","Usage_Name":"AL Message Status","Usage_Types":"Sel"},{"Usage_ID":"1C9","Usage_Name":"AL Contact Sync","Usage_Types":"Sel"},{"Usage_ID":"1CA","Usage_Name":"AL Navigation","Usage_Types":"CA"},{"Usage_ID":"1CB","Usage_Name":"AL Context-aware Desktop Assistant","Usage_Types":"Sel"},{"Usage_ID":"1CC-1FF","Usage_Name":"Reserved","Usage_Types":"Undefined"},{"Usage_ID":"200","Usage_Name":"Generic GUI Application Controls","Usage_Types":"NAry"},{"Usage_ID":"201","Usage_Name":"AC New","Usage_Types":"Sel"},{"Usage_ID":"202","Usage_Name":"AC Open","Usage_Types":"Sel"},{"Usage_ID":"203","Usage_Name":"AC Close","Usage_Types":"Sel"},{"Usage_ID":"204","Usage_Name":"AC Exit","Usage_Types":"Sel"},{"Usage_ID":"205","Usage_Name":"AC Maximize","Usage_Types":"Sel"},{"Usage_ID":"206","Usage_Name":"AC Minimize","Usage_Types":"Sel"},{"Usage_ID":"207","Usage_Name":"AC Save","Usage_Types":"Sel"},{"Usage_ID":"208","Usage_Name":"AC Print","Usage_Types":"Sel"},{"Usage_ID":"209","Usage_Name":"AC Properties","Usage_Types":"Sel"},{"Usage_ID":"20A-219","Usage_Name":"Reserved","Usage_Types":"Undefined"},{"Usage_ID":"21A","Usage_Name":"AC Undo","Usage_Types":"Sel"},{"Usage_ID":"21B","Usage_Name":"AC Copy","Usage_Types":"Sel"},{"Usage_ID":"21C","Usage_Name":"AC Cut","Usage_Types":"Sel"},{"Usage_ID":"21D","Usage_Name":"AC Paste","Usage_Types":"Sel"},{"Usage_ID":"21E","Usage_Name":"AC Select All","Usage_Types":"Sel"},{"Usage_ID":"21F","Usage_Name":"AC Find","Usage_Types":"Sel"},{"Usage_ID":"220","Usage_Name":"AC Find and Replace","Usage_Types":"Sel"},{"Usage_ID":"221","Usage_Name":"AC Search","Usage_Types":"Sel"},{"Usage_ID":"222","Usage_Name":"AC Go To","Usage_Types":"Sel"},{"Usage_ID":"223","Usage_Name":"AC Home","Usage_Types":"Sel"},{"Usage_ID":"224","Usage_Name":"AC Back","Usage_Types":"Sel"},{"Usage_ID":"225","Usage_Name":"AC Forward","Usage_Types":"Sel"},{"Usage_ID":"226","Usage_Name":"AC Stop","Usage_Types":"Sel"},{"Usage_ID":"227","Usage_Name":"AC Refresh","Usage_Types":"Sel"},{"Usage_ID":"228","Usage_Name":"AC Previous Link","Usage_Types":"Sel"},{"Usage_ID":"229","Usage_Name":"AC Next Link","Usage_Types":"Sel"},{"Usage_ID":"22A","Usage_Name":"AC Bookmarks","Usage_Types":"Sel"},{"Usage_ID":"22B","Usage_Name":"AC History","Usage_Types":"Sel"},{"Usage_ID":"22C","Usage_Name":"AC Subscriptions","Usage_Types":"Sel"},{"Usage_ID":"22D","Usage_Name":"AC Zoom In","Usage_Types":"Sel"},{"Usage_ID":"22E","Usage_Name":"AC Zoom Out","Usage_Types":"Sel"},{"Usage_ID":"22F","Usage_Name":"AC Zoom","Usage_Types":"LC"},{"Usage_ID":"230","Usage_Name":"AC Full Screen View","Usage_Types":"Sel"},{"Usage_ID":"231","Usage_Name":"AC Normal View","Usage_Types":"Sel"},{"Usage_ID":"232","Usage_Name":"AC View Toggle","Usage_Types":"Sel"},{"Usage_ID":"233","Usage_Name":"AC Scroll Up","Usage_Types":"Sel"},{"Usage_ID":"234","Usage_Name":"AC Scroll Down","Usage_Types":"Sel"},{"Usage_ID":"235","Usage_Name":"AC Scroll","Usage_Types":"LC"},{"Usage_ID":"236","Usage_Name":"AC Pan Left","Usage_Types":"Sel"},{"Usage_ID":"237","Usage_Name":"AC Pan Right","Usage_Types":"Sel"},{"Usage_ID":"238","Usage_Name":"AC Pan","Usage_Types":"LC"},{"Usage_ID":"239","Usage_Name":"AC New Window","Usage_Types":"Sel"},{"Usage_ID":"23A","Usage_Name":"AC Tile Horizontally","Usage_Types":"Sel"},{"Usage_ID":"23B","Usage_Name":"AC Tile Vertically","Usage_Types":"Sel"},{"Usage_ID":"23C","Usage_Name":"AC Format","Usage_Types":"Sel"},{"Usage_ID":"23D","Usage_Name":"AC Edit","Usage_Types":"Sel"},{"Usage_ID":"23E","Usage_Name":"AC Bold","Usage_Types":"Sel"},{"Usage_ID":"23F","Usage_Name":"AC Italics","Usage_Types":"Sel"},{"Usage_ID":"240","Usage_Name":"AC Underline","Usage_Types":"Sel"},{"Usage_ID":"241","Usage_Name":"AC Strikethrough","Usage_Types":"Sel"},{"Usage_ID":"242","Usage_Name":"AC Subscript","Usage_Types":"Sel"},{"Usage_ID":"243","Usage_Name":"AC Superscript","Usage_Types":"Sel"},{"Usage_ID":"244","Usage_Name":"AC All Caps","Usage_Types":"Sel"},{"Usage_ID":"245","Usage_Name":"AC Rotate","Usage_Types":"Sel"},{"Usage_ID":"246","Usage_Name":"AC Resize","Usage_Types":"Sel"},{"Usage_ID":"247","Usage_Name":"AC Flip Horizontal","Usage_Types":"Sel"},{"Usage_ID":"248","Usage_Name":"AC Flip Vertical","Usage_Types":"Sel"},{"Usage_ID":"249","Usage_Name":"AC Mirror Horizontal","Usage_Types":"Sel"},{"Usage_ID":"24A","Usage_Name":"AC Mirror Vertical","Usage_Types":"Sel"},{"Usage_ID":"24B","Usage_Name":"AC Font Select","Usage_Types":"Sel"},{"Usage_ID":"24C","Usage_Name":"AC Font Color","Usage_Types":"Sel"},{"Usage_ID":"24D","Usage_Name":"AC Font Size","Usage_Types":"Sel"},{"Usage_ID":"24E","Usage_Name":"AC Justify Left","Usage_Types":"Sel"},{"Usage_ID":"24F","Usage_Name":"AC Justify Center H","Usage_Types":"Sel"},{"Usage_ID":"250","Usage_Name":"AC Justify Right","Usage_Types":"Sel"},{"Usage_ID":"251","Usage_Name":"AC Justify Block H","Usage_Types":"Sel"},{"Usage_ID":"252","Usage_Name":"AC Justify Top","Usage_Types":"Sel"},{"Usage_ID":"253","Usage_Name":"AC Justify Center V","Usage_Types":"Sel"},{"Usage_ID":"254","Usage_Name":"AC Justify Bottom","Usage_Types":"Sel"},{"Usage_ID":"255","Usage_Name":"AC Justify Block V","Usage_Types":"Sel"},{"Usage_ID":"256","Usage_Name":"AC Indent Decrease","Usage_Types":"Sel"},{"Usage_ID":"257","Usage_Name":"AC Indent Increase","Usage_Types":"Sel"},{"Usage_ID":"258","Usage_Name":"AC Numbered List","Usage_Types":"Sel"},{"Usage_ID":"259","Usage_Name":"AC Restart Numbering","Usage_Types":"Sel"},{"Usage_ID":"25A","Usage_Name":"AC Bulleted List","Usage_Types":"Sel"},{"Usage_ID":"25B","Usage_Name":"AC Promote","Usage_Types":"Sel"},{"Usage_ID":"25C","Usage_Name":"AC Demote","Usage_Types":"Sel"},{"Usage_ID":"25D","Usage_Name":"AC Yes","Usage_Types":"Sel"},{"Usage_ID":"25E","Usage_Name":"AC No","Usage_Types":"Sel"},{"Usage_ID":"25F","Usage_Name":"AC Cancel","Usage_Types":"Sel"},{"Usage_ID":"260","Usage_Name":"AC Catalog","Usage_Types":"Sel"},{"Usage_ID":"261","Usage_Name":"AC Buy/Checkout","Usage_Types":"Sel"},{"Usage_ID":"262","Usage_Name":"AC Add to Cart","Usage_Types":"Sel"},{"Usage_ID":"263","Usage_Name":"AC Expand","Usage_Types":"Sel"},{"Usage_ID":"264","Usage_Name":"AC Expand All","Usage_Types":"Sel"},{"Usage_ID":"265","Usage_Name":"AC Collapse","Usage_Types":"Sel"},{"Usage_ID":"266","Usage_Name":"AC Collapse All","Usage_Types":"Sel"},{"Usage_ID":"267","Usage_Name":"AC Print Preview","Usage_Types":"Sel"},{"Usage_ID":"268","Usage_Name":"AC Paste Special","Usage_Types":"Sel"},{"Usage_ID":"269","Usage_Name":"AC Insert Mode","Usage_Types":"Sel"},{"Usage_ID":"26A","Usage_Name":"AC Delete","Usage_Types":"Sel"},{"Usage_ID":"26B","Usage_Name":"AC Lock","Usage_Types":"Sel"},{"Usage_ID":"26C","Usage_Name":"AC Unlock","Usage_Types":"Sel"},{"Usage_ID":"26D","Usage_Name":"AC Protect","Usage_Types":"Sel"},{"Usage_ID":"26E","Usage_Name":"AC Unprotect","Usage_Types":"Sel"},{"Usage_ID":"26F","Usage_Name":"AC Attach Comment","Usage_Types":"Sel"},{"Usage_ID":"270","Usage_Name":"AC Delete Comment","Usage_Types":"Sel"},{"Usage_ID":"271","Usage_Name":"AC View Comment","Usage_Types":"Sel"},{"Usage_ID":"272","Usage_Name":"AC Select Word","Usage_Types":"Sel"},{"Usage_ID":"273","Usage_Name":"AC Select Sentence","Usage_Types":"Sel"},{"Usage_ID":"274","Usage_Name":"AC Select Paragraph","Usage_Types":"Sel"},{"Usage_ID":"275","Usage_Name":"AC Select Column","Usage_Types":"Sel"},{"Usage_ID":"276","Usage_Name":"AC Select Row","Usage_Types":"Sel"},{"Usage_ID":"277","Usage_Name":"AC Select Table","Usage_Types":"Sel"},{"Usage_ID":"278","Usage_Name":"AC Select Object","Usage_Types":"Sel"},{"Usage_ID":"279","Usage_Name":"AC Redo/Repeat","Usage_Types":"Sel"},{"Usage_ID":"27A","Usage_Name":"AC Sort","Usage_Types":"Sel"},{"Usage_ID":"27B","Usage_Name":"AC Sort Ascending","Usage_Types":"Sel"},{"Usage_ID":"27C","Usage_Name":"AC Sort Descending","Usage_Types":"Sel"},{"Usage_ID":"27D","Usage_Name":"AC Filter","Usage_Types":"Sel"},{"Usage_ID":"27E","Usage_Name":"AC Set Clock","Usage_Types":"Sel"},{"Usage_ID":"27F","Usage_Name":"AC View Clock","Usage_Types":"Sel"},{"Usage_ID":"280","Usage_Name":"AC Select Time Zone","Usage_Types":"Sel"},{"Usage_ID":"281","Usage_Name":"AC Edit Time Zones","Usage_Types":"Sel"},{"Usage_ID":"282","Usage_Name":"AC Set Alarm","Usage_Types":"Sel"},{"Usage_ID":"283","Usage_Name":"AC Clear Alarm","Usage_Types":"Sel"},{"Usage_ID":"284","Usage_Name":"AC Snooze Alarm","Usage_Types":"Sel"},{"Usage_ID":"285","Usage_Name":"AC Reset Alarm","Usage_Types":"Sel"},{"Usage_ID":"286","Usage_Name":"AC Synchronize","Usage_Types":"Sel"},{"Usage_ID":"287","Usage_Name":"AC Send/Receive","Usage_Types":"Sel"},{"Usage_ID":"288","Usage_Name":"AC Send To","Usage_Types":"Sel"},{"Usage_ID":"289","Usage_Name":"AC Reply","Usage_Types":"Sel"},{"Usage_ID":"28A","Usage_Name":"AC Reply All","Usage_Types":"Sel"},{"Usage_ID":"28B","Usage_Name":"AC Forward Msg","Usage_Types":"Sel"},{"Usage_ID":"28C","Usage_Name":"AC Send","Usage_Types":"Sel"},{"Usage_ID":"28D","Usage_Name":"AC Attach File","Usage_Types":"Sel"},{"Usage_ID":"28E","Usage_Name":"AC Upload","Usage_Types":"Sel"},{"Usage_ID":"28F","Usage_Name":"AC Download (Save Target As)","Usage_Types":"Sel"},{"Usage_ID":"290","Usage_Name":"AC Set Borders","Usage_Types":"Sel"},{"Usage_ID":"291","Usage_Name":"AC Insert Row","Usage_Types":"Sel"},{"Usage_ID":"292","Usage_Name":"AC Insert Column","Usage_Types":"Sel"},{"Usage_ID":"293","Usage_Name":"AC Insert File","Usage_Types":"Sel"},{"Usage_ID":"294","Usage_Name":"AC Insert Picture","Usage_Types":"Sel"},{"Usage_ID":"295","Usage_Name":"AC Insert Object","Usage_Types":"Sel"},{"Usage_ID":"296","Usage_Name":"AC Insert Symbol","Usage_Types":"Sel"},{"Usage_ID":"297","Usage_Name":"AC Save and Close","Usage_Types":"Sel"},{"Usage_ID":"298","Usage_Name":"AC Rename","Usage_Types":"Sel"},{"Usage_ID":"299","Usage_Name":"AC Merge","Usage_Types":"Sel"},{"Usage_ID":"29A","Usage_Name":"AC Split","Usage_Types":"Sel"},{"Usage_ID":"29B","Usage_Name":"AC Disribute Horizontally","Usage_Types":"Sel"},{"Usage_ID":"29C","Usage_Name":"AC Distribute Vertically","Usage_Types":"Sel"},{"Usage_ID":"29D","Usage_Name":"AC Next Keyboard Layout Select","Usage_Types":"Sel"},{"Usage_ID":"29E","Usage_Name":"AC Navigation Guidance","Usage_Types":"Sel"},{"Usage_ID":"29F","Usage_Name":"AC Desktop Show All Windows","Usage_Types":"Sel"},{"Usage_ID":"2A0","Usage_Name":"AC Soft Key Left","Usage_Types":"Sel"},{"Usage_ID":"2A1","Usage_Name":"AC Soft Key Right","Usage_Types":"Sel"},{"Usage_ID":"2A2","Usage_Name":"AC Desktop Show All Applications","Usage_Types":"Sel"},{"Usage_ID":"2A3-2AF","Usage_Name":"Reserved","Usage_Types":"Undefined"},{"Usage_ID":"2B0","Usage_Name":"AC Idle Keep Alive","Usage_Types":"Sel"},{"Usage_ID":"2B1-2BF","Usage_Name":"Reserved","Usage_Types":"Undefined"},{"Usage_ID":"2C0","Usage_Name":"Extended Keyboard Attributes Collection","Usage_Types":"CL"},{"Usage_ID":"2C1","Usage_Name":"Keyboard Form Factor","Usage_Types":"SV"},{"Usage_ID":"2C2","Usage_Name":"Keyboard Key Type","Usage_Types":"SV"},{"Usage_ID":"2C3","Usage_Name":"Keyboard Physical Layout","Usage_Types":"SV"},{"Usage_ID":"2C4","Usage_Name":"Vendor-Specific Keyboard Physical Layout","Usage_Types":"SV"},{"Usage_ID":"2C5","Usage_Name":"Keyboard IETF Language Tag Index","Usage_Types":"SV"},{"Usage_ID":"2C6","Usage_Name":"Implemented Keyboard Input Assist Controls","Usage_Types":"SV"},{"Usage_ID":"2C7","Usage_Name":"Keyboard Input Assist Previous","Usage_Types":"Sel"},{"Usage_ID":"2C8","Usage_Name":"Keyboard Input Assist Next","Usage_Types":"Sel"},{"Usage_ID":"2C9","Usage_Name":"Keyboard Input Assist Previous Group","Usage_Types":"Sel"},{"Usage_ID":"2CA","Usage_Name":"Keyboard Input Assist Next Group","Usage_Types":"CA"},{"Usage_ID":"2CB","Usage_Name":"Keyboard Input Assist Accept","Usage_Types":"Sel"},{"Usage_ID":"2CC","Usage_Name":"Keyboard Input Assist Cancel","Usage_Types":"Sel"},{"Usage_ID":"2CD-2CF","Usage_Name":"Reserved","Usage_Types":"Undefined"},{"Usage_ID":"2D0","Usage_Name":"Privacy Screen Toggle","Usage_Types":"OOC"},{"Usage_ID":"2D1","Usage_Name":"Privacy Screen Level Decrement","Usage_Types":"RTC"},{"Usage_ID":"2D2","Usage_Name":"Privacy Screen Level Increment","Usage_Types":"RTC"},{"Usage_ID":"2D3","Usage_Name":"Privacy Screen Level Minimum","Usage_Types":"OSC"},{"Usage_ID":"2D4","Usage_Name":"Privacy Screen Level Maximum","Usage_Types":"OSC"},{"Usage_ID":"2D5-4FF","Usage_Name":"Reserved","Usage_Types":"Undefined"},{"Usage_ID":"500","Usage_Name":"Contact Edited","Usage_Types":"OOC"},{"Usage_ID":"501","Usage_Name":"Contact Added","Usage_Types":"OOC"},{"Usage_ID":"502","Usage_Name":"Contact Record Active","Usage_Types":"OOC"},{"Usage_ID":"503","Usage_Name":"Contact Index","Usage_Types":"DV"},{"Usage_ID":"504","Usage_Name":"Contact Nickname","Usage_Types":"DV"},{"Usage_ID":"505","Usage_Name":"Contact First Name","Usage_Types":"DV"},{"Usage_ID":"506","Usage_Name":"Contact Last Name","Usage_Types":"DV"},{"Usage_ID":"507","Usage_Name":"Contact Full Name","Usage_Types":"DV"},{"Usage_ID":"508","Usage_Name":"Contact Phone Number Personal","Usage_Types":"DV"},{"Usage_ID":"509","Usage_Name":"Contact Phone Number Business","Usage_Types":"DV"},{"Usage_ID":"50A","Usage_Name":"Contact Phone Number Mobile","Usage_Types":"DV"},{"Usage_ID":"50B","Usage_Name":"Contact Phone Number Pager","Usage_Types":"DV"},{"Usage_ID":"50C","Usage_Name":"Contact Phone Number Fax","Usage_Types":"DV"},{"Usage_ID":"50D","Usage_Name":"Contact Phone Number Other","Usage_Types":"DV"},{"Usage_ID":"50E","Usage_Name":"Contact Email Personal","Usage_Types":"DV"},{"Usage_ID":"50F","Usage_Name":"Contact Email Business","Usage_Types":"DV"},{"Usage_ID":"510","Usage_Name":"Contact Email Other","Usage_Types":"DV"},{"Usage_ID":"511","Usage_Name":"Contact Email Main","Usage_Types":"DV"},{"Usage_ID":"512","Usage_Name":"Contact Speed Dial Number","Usage_Types":"DV"},{"Usage_ID":"513","Usage_Name":"Contact Status Flag","Usage_Types":"DV"},{"Usage_ID":"514","Usage_Name":"Contact Misc.","Usage_Types":"DV"},{"Usage_ID":"515-FFFF","Usage_Name":"Reserved","Usage_Types":"Undefined"}]